Workbook

Sheet BAOCAOKD.TBLDMKHACHHANG
A1: KHACHHANGID | B1: TENKHACHHANG | C1: DIACHI | D1: DIENTHOAI | E1: THONGTINKHAC | F1: THEODOI | G1: THOIGIANCAPNHAT | H1: NGUOICAPNHATID | I1: LOAI | J1: DKKD | K1: GHICHU | L1: NGUOICAPNHATIDMaping
A2: 585 | B2: ABB LTD | F2: 1 | G2: 2021-04-23 10:08:46 | H2: 1548 | L2: =IFERROR(VLOOKUP(H2,users!$A$2:$D$205,2,FALSE),"716336b8-0698-49d0-a65c-b5f45d724290") -> 716336b8-0698-49d0-a65c-b5f45d724198
A3: 586 | B3: BQL bảo trì phần mềm và Tuxedo | F3: 1 | G3: 2021-04-23 10:08:46 | H3: 1548 | L3: =IFERROR(VLOOKUP(H3,users!$A$2:$D$205,2,FALSE),"716336b8-0698-49d0-a65c-b5f45d724290") -> 716336b8-0698-49d0-a65c-b5f45d724198
A4: 587 | B4: Báo Hải Quan | F4: 1 | G4: 2021-04-23 10:08:46 | H4: 1548 | L4: =IFERROR(VLOOKUP(H4,users!$A$2:$D$205,2,FALSE),"716336b8-0698-49d0-a65c-b5f45d724290") -> 716336b8-0698-49d0-a65c-b5f45d724198
A5: 588 | B5: Bệnh viện Hữu nghị Việt Đức | F5: 1 | G5: 2021-04-23 10:07:50 | H5: 1548 | L5: =IFERROR(VLOOKUP(H5,users!$A$2:$D$205,2,FALSE),"716336b8-0698-49d0-a65c-b5f45d724290") -> 716336b8-0698-49d0-a65c-b5f45d724198
A6: 589 | B6: Bệnh viện Nhi Trung Ương | F6: 1 | G6: 2021-04-23 09:47:54 | H6: 1548 | L6: =IFERROR(VLOOKUP(H6,users!$A$2:$D$205,2,FALSE),"716336b8-0698-49d0-a65c-b5f45d724290") -> 716336b8-0698-49d0-a65c-b5f45d724198
A7: 591 | B7: Bệnh viện Phổi Trung Ương - Quỹ toàn cầu phòng chống lao GĐ 2018-2020 | F7: 1 | G7: 2021-04-23 10:09:13 | H7: 1548 | L7: =IFERROR(VLOOKUP(H7,users!$A$2:$D$205,2,FALSE),"716336b8-0698-49d0-a65c-b5f45d724290") -> 716336b8-0698-49d0-a65c-b5f45d724198
A8: 592 | B8: Bộ Tư lệnh 86/BQP | F8: 1 | G8: 2021-04-23 10:08:46 | H8: 1548 | L8: =IFERROR(VLOOKUP(H8,users!$A$2:$D$205,2,FALSE),"716336b8-0698-49d0-a65c-b5f45d724290") -> 716336b8-0698-49d0-a65c-b5f45d724198
A9: 593 | B9: BQL DA Trường Đại học Việt Đức | F9: 1 | G9: 2021-04-23 10:08:46 | H9: 1548 | L9: =IFERROR(VLOOKUP(H9,users!$A$2:$D$205,2,FALSE),"716336b8-0698-49d0-a65c-b5f45d724290") -> 716336b8-0698-49d0-a65c-b5f45d724198
A10: 594 | B10: CN Công ty cổ phần Diana Unicharm - Bắc Ninh | F10: 1 | G10: 2021-04-23 10:14:08 | H10: 1548 | L10: =IFERROR(VLOOKUP(H10,users!$A$2:$D$205,2,FALSE),"716336b8-0698-49d0-a65c-b5f45d724290") -> 716336b8-0698-49d0-a65c-b5f45d724198
A11: 595 | B11: CN Trung tâm CNTT Tập đoàn Bảo Việt | F11: 1 | G11: 2021-04-23 10:12:31 | H11: 1548 | L11: =IFERROR(VLOOKUP(H11,users!$A$2:$D$205,2,FALSE),"716336b8-0698-49d0-a65c-b5f45d724290") -> 716336b8-0698-49d0-a65c-b5f45d724198
A12: 596 | B12: CN Công ty cổ phần Giao nhận và vận chuyển Indo Trần | F12: 1 | G12: 2021-04-23 02:10:35 | H12: 1548 | L12: =IFERROR(VLOOKUP(H12,users!$A$2:$D$205,2,FALSE),"716336b8-0698-49d0-a65c-b5f45d724290") -> 716336b8-0698-49d0-a65c-b5f45d724198
A13: 597 | B13: CN TCT Điện lực TP HCM TNHH - Công ty CNTT Điện lực TP HCM | F13: 1 | G13: 2021-04-23 10:13:00 | H13: 1548 | L13: =IFERROR(VLOOKUP(H13,users!$A$2:$D$205,2,FALSE),"716336b8-0698-49d0-a65c-b5f45d724290") -> 716336b8-0698-49d0-a65c-b5f45d724198
... A104: 726 | B104: Ngân hàng TMCP Công thương Việt Nam (VietinBank) | F104: 1 | G104: 2021-04-23 02:56:26 | H104: 1548 | L104: =IFERROR(VLOOKUP(H104,users!$A$2:$D$205,2,FALSE),"716336b8-0698-49d0-a65c-b5f45d724290") -> 716336b8-0698-49d0-a65c-b5f45d724198
A105: 788 | B105: Khachhang-Dum-01 | C105: 152 Thuy Khue, Tay Ho, Ha Noi | F105: 1 | G105: 2021-04-28 02:33:49 | H105: 1605 | L105: =IFERROR(VLOOKUP(H105,users!$A$2:$D$205,2,FALSE),"716336b8-0698-49d0-a65c-b5f45d724290") -> 716336b8-0698-49d0-a65c-b5f45d724290
A106: 728 | B106: Ngân hàng TMCP Đông Nam Á (SeABank) | F106: 1 | G106: 2021-04-23 04:34:12 | H106: 1548 | L106: =IFERROR(VLOOKUP(H106,users!$A$2:$D$205,2,FALSE),"716336b8-0698-49d0-a65c-b5f45d724290") -> 716336b8-0698-49d0-a65c-b5f45d724198
A107: 729 | B107: Ngân hàng TMCP Kiên Long (KienLong Bank) | F107: 1 | G107: 2021-04-23 02:57:19 | H107: 1548 | L107: =IFERROR(VLOOKUP(H107,users!$A$2:$D$205,2,FALSE),"716336b8-0698-49d0-a65c-b5f45d724290") -> 716336b8-0698-49d0-a65c-b5f45d724198
A108: 730 | B108: Ngân hàng TMCP Kỹ thương Việt Nam (Techcombank) | F108: 1 | G108: 2021-04-23 02:57:45 | H108: 1548 | L108: =IFERROR(VLOOKUP(H108,users!$A$2:$D$205,2,FALSE),"716336b8-0698-49d0-a65c-b5f45d724290") -> 716336b8-0698-49d0-a65c-b5f45d724198
A109: 731 | B109: Ngân hàng TMCP Ngoại thương Việt Nam (Vietcombank) | F109: 1 | G109: 2021-04-23 02:58:05 | H109: 1548 | L109: =IFERROR(VLOOKUP(H109,users!$A$2:$D$205,2,FALSE),"716336b8-0698-49d0-a65c-b5f45d724290") -> 716336b8-0698-49d0-a65c-b5f45d724198
A110: 732 | B110: Ngân hàng TMCP Phương Đông (OCB) | F110: 1 | G110: 2021-04-23 04:24:17 | H110: 1548 | L110: =IFERROR(VLOOKUP(H110,users!$A$2:$D$205,2,FALSE),"716336b8-0698-49d0-a65c-b5f45d724290") -> 716336b8-0698-49d0-a65c-b5f45d724198
A111: 733 | B111: Ngân hàng TMCP Quốc dân (NCB) | F111: 1 | G111: 2021-04-23 10:08:46 | H111: 1548 | L111: =IFERROR(VLOOKUP(H111,users!$A$2:$D$205,2,FALSE),"716336b8-0698-49d0-a65c-b5f45d724290") -> 716336b8-0698-49d0-a65c-b5f45d724198
A112: 734 | B112: Ngân hàng TMCP Quốc Tế Việt Nam (VIB) | F112: 1 | G112: 2021-04-23 10:08:46 | H112: 1548 | L112: =IFERROR(VLOOKUP(H112,users!$A$2:$D$205,2,FALSE),"716336b8-0698-49d0-a65c-b5f45d724290") -> 716336b8-0698-49d0-a65c-b5f45d724198
A113: 735 | B113: Ngân hàng TMCP Sài Gòn - Hà Nội (SHB) | F113: 1 | G113: 2021-04-23 04:25:31 | H113: 1548 | L113: =IFERROR(VLOOKUP(H113,users!$A$2:$D$205,2,FALSE),"716336b8-0698-49d0-a65c-b5f45d724290") -> 716336b8-0698-49d0-a65c-b5f45d724198
A114: 736 | B114: Ngân hàng TMCP Sài Gòn công thương (Saigonbank) | F114: 1 | G114: 2021-04-23 04:27:39 | H114: 1548 | L114: =IFERROR(VLOOKUP(H114,users!$A$2:$D$205,2,FALSE),"716336b8-0698-49d0-a65c-b5f45d724290") -> 716336b8-0698-49d0-a65c-b5f45d724198
A115: 737 | B115: Ngân hàng TMCP Sài Gòn Thương Tín (Sacombank) | F115: 1 | G115: 2021-04-23 04:28:03 | H115: 1548 | L115: =IFERROR(VLOOKUP(H115,users!$A$2:$D$205,2,FALSE),"716336b8-0698-49d0-a65c-b5f45d724290") -> 716336b8-0698-49d0-a65c-b5f45d724198
A116: 790 | B116: Công ty cổ phần Văn phòng phẩm Hồng Hà | F116: 1 | G116: 2021-05-03 08:09:35 | H116: 1548 | L116: =IFERROR(VLOOKUP(H116,users!$A$2:$D$205,2,FALSE),"716336b8-0698-49d0-a65c-b5f45d724290") -> 716336b8-0698-49d0-a65c-b5f45d724198
A117: 739 | B117: Ngân hàng TMCP Việt Nam Thịnh Vượng (VPBank) | F117: 1 | G117: 2021-04-23 04:28:50 | H117: 1548 | L117: =IFERROR(VLOOKUP(H117,users!$A$2:$D$205,2,FALSE),"716336b8-0698-49d0-a65c-b5f45d724290") -> 716336b8-0698-49d0-a65c-b5f45d724198
... A140: 762 | B140: Tổng công ty Hóa dầu Petrolimex - CTCP (PLC) | F140: 1 | G140: 2021-04-24 05:34:09 | H140: 1548 | L140: =IFERROR(VLOOKUP(H140,users!$A$2:$D$205,2,FALSE),"716336b8-0698-49d0-a65c-b5f45d724290") -> 716336b8-0698-49d0-a65c-b5f45d724198
A141: 763 | B141: Tổng công ty Khí Việt Nam - CTCP (PV GAS) | C141: Tầng 12, 12A, 14 và tầng 15, Tòa nhà PV GAS, số 673 đường Nguyễn Hữu Thọ, xã Phước Kiển, huyện Nhà Bè, TP.HCM | D141: +84.28. 3781 6777 Fax: +84.28. 3781 5666 | F141: 1 | G141: 2021-04-24 05:38:42 | H141: 1548 | L141: =IFERROR(VLOOKUP(H141,users!$A$2:$D$205,2,FALSE),"716336b8-0698-49d0-a65c-b5f45d724290") -> 716336b8-0698-49d0-a65c-b5f45d724198
A142: 764 | B142: Tổng công ty Viglacera - CTCP | F142: 1 | G142: 2021-04-24 05:34:54 | H142: 1548 | L142: =IFERROR(VLOOKUP(H142,users!$A$2:$D$205,2,FALSE),"716336b8-0698-49d0-a65c-b5f45d724290") -> 716336b8-0698-49d0-a65c-b5f45d724198
A143: 765 | B143: Trung tâm Chính phủ điện tử | F143: 1 | G143: 2021-04-24 05:25:30 | H143: 1548 | L143: =IFERROR(VLOOKUP(H143,users!$A$2:$D$205,2,FALSE),"716336b8-0698-49d0-a65c-b5f45d724290") -> 716336b8-0698-49d0-a65c-b5f45d724198
A144: 766 | B144: Trung tâm Internet Việt Nam (VNNIC) | F144: 1 | G144: 2021-04-23 08:58:14 | H144: 1577 | L144: =IFERROR(VLOOKUP(H144,users!$A$2:$D$205,2,FALSE),"716336b8-0698-49d0-a65c-b5f45d724290") -> 716336b8-0698-49d0-a65c-b5f45d724099
A145: 767 | B145: Trung tâm Lưu ký chứng khoán Việt Nam (VSD) | F145: 1 | G145: 2021-04-24 05:26:07 | H145: 1548 | L145: =IFERROR(VLOOKUP(H145,users!$A$2:$D$205,2,FALSE),"716336b8-0698-49d0-a65c-b5f45d724290") -> 716336b8-0698-49d0-a65c-b5f45d724198
A146: 792 | B146: Công ty Tài chính TNHH MTV Lotte Việt Nam (Lotte Finance Vietnam) | F146: 1 | G146: 2021-05-04 12:53:36 | H146: 1548 | L146: =IFERROR(VLOOKUP(H146,users!$A$2:$D$205,2,FALSE),"716336b8-0698-49d0-a65c-b5f45d724290") -> 716336b8-0698-49d0-a65c-b5f45d724198
A147: 769 | B147: Trung tâm Thông tin và Dự báo kinh tế - xã hội Quốc gia (NCIF) | F147: 1 | G147: 2021-04-24 05:24:17 | H147: 1548 | L147: =IFERROR(VLOOKUP(H147,users!$A$2:$D$205,2,FALSE),"716336b8-0698-49d0-a65c-b5f45d724290") -> 716336b8-0698-49d0-a65c-b5f45d724198
A148: 770 | B148: Trung tâm Tin học - Kiểm toán Nhà nước (KTNN) | F148: 1 | G148: 2021-04-24 05:32:07 | H148: 1548 | L148: =IFERROR(VLOOKUP(H148,users!$A$2:$D$205,2,FALSE),"716336b8-0698-49d0-a65c-b5f45d724290") -> 716336b8-0698-49d0-a65c-b5f45d724198
A149: 771 | B149: Trung tâm Tin học và công nghệ truyền hình (VTV) | F149: 1 | G149: 2021-05-28 09:48:44 | H149: 1548 | L149: =IFERROR(VLOOKUP(H149,users!$A$2:$D$205,2,FALSE),"716336b8-0698-49d0-a65c-b5f45d724290") -> 716336b8-0698-49d0-a65c-b5f45d724198
A150: 772 | B150: Trung tâm Ứng dụng và phát triển công nghệ địa chính | F150: 1 | G150: 2021-04-24 05:32:38 | H150: 1548 | L150: =IFERROR(VLOOKUP(H150,users!$A$2:$D$205,2,FALSE),"716336b8-0698-49d0-a65c-b5f45d724290") -> 716336b8-0698-49d0-a65c-b5f45d724198
A151: 773 | B151: Trường Đại học Bách Khoa | F151: 1 | G151: 2021-04-23 10:08:46 | H151: 1548 | L151: =IFERROR(VLOOKUP(H151,users!$A$2:$D$205,2,FALSE),"716336b8-0698-49d0-a65c-b5f45d724290") -> 716336b8-0698-49d0-a65c-b5f45d724198
A152: 774 | B152: Trường Đại học Luật TP HCM | F152: 1 | G152: 2021-04-23 10:08:46 | H152: 1548 | L152: =IFERROR(VLOOKUP(H152,users!$A$2:$D$205,2,FALSE),"716336b8-0698-49d0-a65c-b5f45d724290") -> 716336b8-0698-49d0-a65c-b5f45d724198
A153: 775 | B153: Trường Đại Học Kinh Tế - Công Nghệ Thái Nguyên | C153: phường Đồng Bẩm, thành phố Thái Nguyên, tỉnh Thái Nguyên | F153: 1 | G153: 2022-04-19 11:22:22 | H153: 1621 | J153: 4601266308 | L153: =IFERROR(VLOOKUP(H153,users!$A$2:$D$205,2,FALSE),"716336b8-0698-49d0-a65c-b5f45d724290") -> 716336b8-0698-49d0-a65c-b5f45d724290
A154: 776 | B154: TT CNTT - Ngân hàng TMCP Đầu tư và Phát triển Việt Nam (BIDV) | F154: 1 | G154: 2021-04-24 05:20:59 | H154: 1548 | L154: =IFERROR(VLOOKUP(H154,users!$A$2:$D$205,2,FALSE),"716336b8-0698-49d0-a65c-b5f45d724290") -> 716336b8-0698-49d0-a65c-b5f45d724198
A155: 777 | B155: TT Thông tin tín dụng Quốc gia Việt Nam (CIC) | F155: 1 | G155: 2021-04-24 05:21:35 | H155: 1548 | L155: =IFERROR(VLOOKUP(H155,users!$A$2:$D$205,2,FALSE),"716336b8-0698-49d0-a65c-b5f45d724290") -> 716336b8-0698-49d0-a65c-b5f45d724198
A156: 778 | B156: TT CNTT - Ngân hàng Nông nghiệp và Phát triển nông thôn Việt Nam (Agribank) | F156: 1 | G156: 2021-04-24 05:22:40 | H156: 1548 | L156: =IFERROR(VLOOKUP(H156,users!$A$2:$D$205,2,FALSE),"716336b8-0698-49d0-a65c-b5f45d724290") -> 716336b8-0698-49d0-a65c-b5f45d724198
A157: 779 | B157: Văn phòng Dự án Tổ chức Blue Dragon Children's Foundation (BDCF) Ô-XTƠ-RÂY-LI-A tại Việt Nam | F157: 1 | G157: 2021-04-19 11:16:44 | H157: 21 | L157: =IFERROR(VLOOKUP(H157,users!$A$2:$D$205,2,FALSE),"716336b8-0698-49d0-a65c-b5f45d724290") -> 716336b8-0698-49d0-a65c-b5f45d724195
A158: 780 | B158: Viện Nghiên cứu ứng dụng công nghệ CMC (CIST) | F158: 1 | G158: 2021-04-24 05:43:47 | H158: 1548 | L158: =IFERROR(VLOOKUP(H158,users!$A$2:$D$205,2,FALSE),"716336b8-0698-49d0-a65c-b5f45d724290") -> 716336b8-0698-49d0-a65c-b5f45d724198
A159: 781 | B159: Viện Toán Học | F159: 1 | G159: 2021-04-23 10:08:46 | H159: 1548 | L159: =IFERROR(VLOOKUP(H159,users!$A$2:$D$205,2,FALSE),"716336b8-0698-49d0-a65c-b5f45d724290") -> 716336b8-0698-49d0-a65c-b5f45d724198
A160: 797 | B160: Dệt may Bảo Minh | F160: 1 | G160: 2021-05-05 01:25:14 | H160: 1548 | L160: =IFERROR(VLOOKUP(H160,users!$A$2:$D$205,2,FALSE),"716336b8-0698-49d0-a65c-b5f45d724290") -> 716336b8-0698-49d0-a65c-b5f45d724198
A161: 783 | B161: Widia Shinki Vietnam LLC | F161: 1 | G161: 2021-04-24 05:45:07 | H161: 1548 | L161: =IFERROR(VLOOKUP(H161,users!$A$2:$D$205,2,FALSE),"716336b8-0698-49d0-a65c-b5f45d724290") -> 716336b8-0698-49d0-a65c-b5f45d724198
A162: 784 | B162: Ngân hàng TMCP Đầu tư và Phát triển Việt Nam (BIDV) | C162: Tháp BIDV, số 35 Hàng Vôi, Phường Lý Thái Tổ, Quận Hoàn Kiếm, Thành phố Hà Nội | F162: 1 | G162: 2021-04-28 09:33:45 | H162: 1577 | J162: 0100150619 | L162: =IFERROR(VLOOKUP(H162,users!$A$2:$D$205,2,FALSE),"716336b8-0698-49d0-a65c-b5f45d724290") -> 716336b8-0698-49d0-a65c-b5f45d724099
A163: 798 | B163: Công ty cổ phần Sở hữu công nghiệp Investip | F163: 1 | G163: 2021-05-05 02:23:05 | H163: 1548 | L163: =IFERROR(VLOOKUP(H163,users!$A$2:$D$205,2,FALSE),"716336b8-0698-49d0-a65c-b5f45d724290") -> 716336b8-0698-49d0-a65c-b5f45d724198
A164: 801 | B164: Bệnh viện Đa khoa Bắc Ninh | F164: 1 | G164: 2021-05-05 04:45:24 | H164: 1548 | L164: =IFERROR(VLOOKUP(H164,users!$A$2:$D$205,2,FALSE),"716336b8-0698-49d0-a65c-b5f45d724290") -> 716336b8-0698-49d0-a65c-b5f45d724198
A165: 802 | B165: Công ty Cổ phần đầu tư phát triển máy Việt Nam (VIMID) | C165: BT1-07 Khu đô thị mới An Hưng, đường Tố Hữu, Phường Dương Nội, Quận Hà Đông, Thành Phố Hà Nội, Việt Nam | F165: 1 | G165: 2021-05-07 08:41:03 | H165: 1528 | L165: =IFERROR(VLOOKUP(H165,users!$A$2:$D$205,2,FALSE),"716336b8-0698-49d0-a65c-b5f45d724290") -> 716336b8-0698-49d0-a65c-b5f45d724116
A166: 804 | B166: Hoà Phát | C166: 66 Nguyễn Du, Quận Hai Bà Trưng, Hà Nội | F166: 1 | G166: 2021-05-07 02:12:29 | H166: 1525 | L166: =IFERROR(VLOOKUP(H166,users!$A$2:$D$205,2,FALSE),"716336b8-0698-49d0-a65c-b5f45d724290") -> 716336b8-0698-49d0-a65c-b5f45d724115
A167: 805 | B167: Công ty Cổ phần Tập đoàn T&T | C167: 2A Phạm Sư Mạnh, Quận Hoàn Kiếm, Hà Nội | F167: 1 | G167: 2021-05-07 02:14:15 | H167: 1525 | L167: =IFERROR(VLOOKUP(H167,users!$A$2:$D$205,2,FALSE),"716336b8-0698-49d0-a65c-b5f45d724290") -> 716336b8-0698-49d0-a65c-b5f45d724115
A168: 806 | B168: Công ty cổ phần Andes E&C Việt Nam | F168: 1 | G168: 2021-05-08 05:18:10 | H168: 1548 | L168: =IFERROR(VLOOKUP(H168,users!$A$2:$D$205,2,FALSE),"716336b8-0698-49d0-a65c-b5f45d724290") -> 716336b8-0698-49d0-a65c-b5f45d724198
A169: 807 | B169: Tập đoàn Vàng bạc đá quý DOJI | F169: 1 | G169: 2021-05-08 06:06:31 | H169: 1548 | L169: =IFERROR(VLOOKUP(H169,users!$A$2:$D$205,2,FALSE),"716336b8-0698-49d0-a65c-b5f45d724290") -> 716336b8-0698-49d0-a65c-b5f45d724198
A170: 812 | B170: Công ty TNHH Quản lý nợ và khai thác tài sản Ngân hàng TMCP Quân đội (MBAMC) | F170: 1 | G170: 2021-05-11 04:22:16 | H170: 1548 | L170: =IFERROR(VLOOKUP(H170,users!$A$2:$D$205,2,FALSE),"716336b8-0698-49d0-a65c-b5f45d724290") -> 716336b8-0698-49d0-a65c-b5f45d724198
A171: 817 | B171: Sở TTTT Ninh Bình | F171: 1 | G171: 2021-05-15 10:55:59 | H171: 1548 | L171: =IFERROR(VLOOKUP(H171,users!$A$2:$D$205,2,FALSE),"716336b8-0698-49d0-a65c-b5f45d724290") -> 716336b8-0698-49d0-a65c-b5f45d724198
A172: 608 | B172: Công ty cổ phần Chứng khoán Bảo Việt (BVSC) | F172: 1 | G172: 2021-04-23 01:32:48 | H172: 1548 | L172: =IFERROR(VLOOKUP(H172,users!$A$2:$D$205,2,FALSE),"716336b8-0698-49d0-a65c-b5f45d724290") -> 716336b8-0698-49d0-a65c-b5f45d724198
A173: 786 | B173: Công ty cổ phần Tập đoàn HIPT | C173: Số 152 Thụy Khuê, Tây Hồ, Hà Nội | E173: MST: 0100364579 | F173: 1 | G173: 2021-04-23 01:40:16 | H173: 1548 | L173: =IFERROR(VLOOKUP(H173,users!$A$2:$D$205,2,FALSE),"716336b8-0698-49d0-a65c-b5f45d724290") -> 716336b8-0698-49d0-a65c-b5f45d724198
A174: 617 | B174: Công ty cổ phần Đầu tư NHV | F174: 1 | G174: 2021-04-23 02:35:59 | H174: 1548 | L174: =IFERROR(VLOOKUP(H174,users!$A$2:$D$205,2,FALSE),"716336b8-0698-49d0-a65c-b5f45d724290") -> 716336b8-0698-49d0-a65c-b5f45d724198
A175: 815 | B175: Công ty cổ phần Công nghệ Vinorsoft | F175: 1 | G175: 2021-05-15 09:54:01 | H175: 1548 | L175: =IFERROR(VLOOKUP(H175,users!$A$2:$D$205,2,FALSE),"716336b8-0698-49d0-a65c-b5f45d724290") -> 716336b8-0698-49d0-a65c-b5f45d724198
A176: 789 | B176: khachhang-dum-02 | C176: 152 Thuy Khue | F176: 1 | G176: 2021-04-29 08:56:22 | H176: 1605 | L176: =IFERROR(VLOOKUP(H176,users!$A$2:$D$205,2,FALSE),"716336b8-0698-49d0-a65c-b5f45d724290") -> 716336b8-0698-49d0-a65c-b5f45d724290
A177: 793 | B177: Công ty cổ phần Phát triển chăn nuôi Hòa Phát | F177: 1 | G177: 2021-05-04 04:42:28 | H177: 1548 | L177: =IFERROR(VLOOKUP(H177,users!$A$2:$D$205,2,FALSE),"716336b8-0698-49d0-a65c-b5f45d724290") -> 716336b8-0698-49d0-a65c-b5f45d724198
A178: 794 | B178: Công ty cổ phần Giáo dục và đào tạo Tinh hoa toàn cầu (GEET) | F178: 1 | G178: 2021-05-04 04:44:42 | H178: 1548 | L178: =IFERROR(VLOOKUP(H178,users!$A$2:$D$205,2,FALSE),"716336b8-0698-49d0-a65c-b5f45d724290") -> 716336b8-0698-49d0-a65c-b5f45d724198
A179: 795 | B179: Trường Cao đẳng Công nghệ và kinh tế công nghiệp (IETC) | F179: 1 | G179: 2021-05-04 04:48:57 | H179: 1548 | L179: =IFERROR(VLOOKUP(H179,users!$A$2:$D$205,2,FALSE),"716336b8-0698-49d0-a65c-b5f45d724290") -> 716336b8-0698-49d0-a65c-b5f45d724198
A180: 814 | B180: Công ty Cổ phần Logistics Hàng không (ALS) | F180: 1 | G180: 2021-05-15 09:49:09 | H180: 1548 | L180: =IFERROR(VLOOKUP(H180,users!$A$2:$D$205,2,FALSE),"716336b8-0698-49d0-a65c-b5f45d724290") -> 716336b8-0698-49d0-a65c-b5f45d724198
A181: 818 | B181: Công ty Thiết bị khoa học Sơn Hải | C181: Townhouse 14, Number 4, Van Khe New Urban Area, Le Van Luong road, Ha Dong Dist. Hanoi, Vietnam | F181: 1 | G181: 2021-05-17 09:16:09 | H181: 1528 | L181: =IFERROR(VLOOKUP(H181,users!$A$2:$D$205,2,FALSE),"716336b8-0698-49d0-a65c-b5f45d724290") -> 716336b8-0698-49d0-a65c-b5f45d724116
A182: 819 | B182: Cục Tin Học Hóa- Bộ Thông tin và truyền Thông | C182: Trụ sở chính: Tầng 21, Tòa nhà Cục Viễn thông, số 68 đường Dương Đình Nghệ, Yên Hòa, Cầu Giấy, Hà Nội. | D182: 024.37821766 | F182: 1 | G182: 2021-05-18 09:27:56 | H182: 1516 | L182: =IFERROR(VLOOKUP(H182,users!$A$2:$D$205,2,FALSE),"716336b8-0698-49d0-a65c-b5f45d724290") -> 716336b8-0698-49d0-a65c-b5f45d724178
A183: 821 | B183: Công ty TNHH Viettel - CHT | F183: 1 | G183: 2021-05-26 10:54:56 | H183: 1523 | L183: =IFERROR(VLOOKUP(H183,users!$A$2:$D$205,2,FALSE),"716336b8-0698-49d0-a65c-b5f45d724290") -> 716336b8-0698-49d0-a65c-b5f45d724259
A184: 822 | B184: Trung tâm kinh doanh Doanh Nghiệp - HIPT | F184: 1 | G184: 2021-05-28 03:36:16 | H184: 1535 | L184: =IFERROR(VLOOKUP(H184,users!$A$2:$D$205,2,FALSE),"716336b8-0698-49d0-a65c-b5f45d724290") -> 716336b8-0698-49d0-a65c-b5f45d724119
A185: 826 | B185: KCN Bình Sơn - Quảng Ngãi | F185: 1 | G185: 2021-06-07 05:50:23 | H185: 1548 | L185: =IFERROR(VLOOKUP(H185,users!$A$2:$D$205,2,FALSE),"716336b8-0698-49d0-a65c-b5f45d724290") -> 716336b8-0698-49d0-a65c-b5f45d724198
A186: 828 | B186: Viện kiểm sát nhân dân tối cao | F186: 1 | G186: 2021-06-08 04:04:10 | H186: 21 | L186: =IFERROR(VLOOKUP(H186,users!$A$2:$D$205,2,FALSE),"716336b8-0698-49d0-a65c-b5f45d724290") -> 716336b8-0698-49d0-a65c-b5f45d724195
A187: 832 | B187: Tổng Công ty cổ phần bảo hiểm Petrolimex | C187: Tầng 21, 22 tòa nhà MIPEC TOWER, số 229 phố tây sơn, Quận Đống Đa, Thành phố Hà Nội. | D187: 02437760867, 02437760923 | F187: 1 | G187: 2021-06-14 04:06:18 | H187: 1524 | L187: =IFERROR(VLOOKUP(H187,users!$A$2:$D$205,2,FALSE),"716336b8-0698-49d0-a65c-b5f45d724290") -> 716336b8-0698-49d0-a65c-b5f45d724274
A188: 842 | B188: Công ty TNHH MCNEX VINA | F188: 1 | G188: 2021-07-04 10:12:37 | H188: 1548 | L188: =IFERROR(VLOOKUP(H188,users!$A$2:$D$205,2,FALSE),"716336b8-0698-49d0-a65c-b5f45d724290") -> 716336b8-0698-49d0-a65c-b5f45d724198
A189: 850 | B189: Ascend group | C189: tầng 9 tòa sông hồng, 165 Thái Hà, Đống Đa, HN | F189: 1 | G189: 2021-07-12 12:58:00 | H189: 1516 | L189: =IFERROR(VLOOKUP(H189,users!$A$2:$D$205,2,FALSE),"716336b8-0698-49d0-a65c-b5f45d724290") -> 716336b8-0698-49d0-a65c-b5f45d724178
A190: 852 | B190: Viện Nghiên cứu chiến lược chính sách công thương | C190: Số 17 Yết Kiêu, Phường Nguyễn Du, Quận Hai Bà Trưng, Hà Nội | D190: 024.39346029 | E190: Mã ĐVQHNS: 1054054 | F190: 1 | G190: 2021-07-13 02:05:20 | H190: 1508 | L190: =IFERROR(VLOOKUP(H190,users!$A$2:$D$205,2,FALSE),"716336b8-0698-49d0-a65c-b5f45d724290") -> 716336b8-0698-49d0-a65c-b5f45d724244
A191: 853 | B191: CÔNG TY TNHH CHINH THÁI | C191: Thôn Trang Quan, xã An Đồng, huyện An Dương, Thành Phố Hải Phòng | D191: 0989 423 615 | F191: 1 | G191: 2021-07-13 02:16:28 | H191: 1536 | J191: 0200808806 | L191: =IFERROR(VLOOKUP(H191,users!$A$2:$D$205,2,FALSE),"716336b8-0698-49d0-a65c-b5f45d724290") -> 716336b8-0698-49d0-a65c-b5f45d724120
A192: 854 | B192: ABCIS | F192: 1 | G192: 2021-07-13 03:55:44 | H192: 1671 | L192: =IFERROR(VLOOKUP(H192,users!$A$2:$D$205,2,FALSE),"716336b8-0698-49d0-a65c-b5f45d724290") -> 716336b8-0698-49d0-a65c-b5f45d724107
A193: 864 | B193: Thanh tra Chính phủ | F193: 1 | G193: 2021-07-16 12:45:56 | H193: 21 | L193: =IFERROR(VLOOKUP(H193,users!$A$2:$D$205,2,FALSE),"716336b8-0698-49d0-a65c-b5f45d724290") -> 716336b8-0698-49d0-a65c-b5f45d724195
A194: 866 | B194: CÔNG TY CỔ PHẦN THỰC PHẨM SỮA TH | C194: Xã Nghĩa Sơn, Huyện Nghĩa Đàn, Tỉnh Nghệ An | F194: 1 | G194: 2021-07-27 11:10:53 | H194: 1536 | J194: 0103414411 | L194: =IFERROR(VLOOKUP(H194,users!$A$2:$D$205,2,FALSE),"716336b8-0698-49d0-a65c-b5f45d724290") -> 716336b8-0698-49d0-a65c-b5f45d724120
A195: 889 | B195: Bệnh viện Trung ương Huế | C195: Số 16 Lê Lợi, Phường Vĩnh Ninh, Thành phố Huếế | F195: 1 | G195: 2021-08-03 04:32:19 | H195: 1524 | L195: =IFERROR(VLOOKUP(H195,users!$A$2:$D$205,2,FALSE),"716336b8-0698-49d0-a65c-b5f45d724290") -> 716336b8-0698-49d0-a65c-b5f45d724274
A196: 891 | B196: Công ty Xi măng Vissai | F196: 1 | G196: 2021-08-05 10:37:42 | H196: 1510 | L196: =IFERROR(VLOOKUP(H196,users!$A$2:$D$205,2,FALSE),"716336b8-0698-49d0-a65c-b5f45d724290") -> 716336b8-0698-49d0-a65c-b5f45d724293
A197: 906 | B197: Công ty TNHH MTV VIPCO Hạ Long | F197: 1 | G197: 2021-08-09 03:24:14 | H197: 1528 | L197: =IFERROR(VLOOKUP(H197,users!$A$2:$D$205,2,FALSE),"716336b8-0698-49d0-a65c-b5f45d724290") -> 716336b8-0698-49d0-a65c-b5f45d724116
A198: 948 | B198: Hoa Sen Group | F198: 1 | G198: 2021-09-02 11:47:33 | H198: 1528 | L198: =IFERROR(VLOOKUP(H198,users!$A$2:$D$205,2,FALSE),"716336b8-0698-49d0-a65c-b5f45d724290") -> 716336b8-0698-49d0-a65c-b5f45d724116
A199: 949 | B199: Công ty cổ phần lọc hóa dầu Bình Sơn (BSR) | F199: 1 | G199: 2021-09-06 10:27:24 | H199: 1561 | L199: =IFERROR(VLOOKUP(H199,users!$A$2:$D$205,2,FALSE),"716336b8-0698-49d0-a65c-b5f45d724290") -> 716336b8-0698-49d0-a65c-b5f45d724213
A200: 950 | B200: Ngân hàng Bản Việt (BVB) | C200: 412 Nguyễn Thị Minh Khai, Phường 5, Quận 3, TP.HCM | F200: 1 | G200: 2021-09-13 04:14:24 | H200: 1592 | L200: =IFERROR(VLOOKUP(H200,users!$A$2:$D$205,2,FALSE),"716336b8-0698-49d0-a65c-b5f45d724290") -> 716336b8-0698-49d0-a65c-b5f45d724237
A201: 951 | B201: Công ty TNHH MTV Viễn thông Quốc tế FPT | F201: 1 | G201: 2021-09-14 11:07:28 | H201: 1515 | L201: =IFERROR(VLOOKUP(H201,users!$A$2:$D$205,2,FALSE),"716336b8-0698-49d0-a65c-b5f45d724290") -> 716336b8-0698-49d0-a65c-b5f45d724113
A202: 959 | B202: Thông tấn xã Việt nam (TTXVN) | C202: Số 05 Lý Thường Kiệt - Hà Nội - Việt Nam | F202: 1 | G202: 2021-09-23 06:07:46 | H202: 1519 | L202: =IFERROR(VLOOKUP(H202,users!$A$2:$D$205,2,FALSE),"716336b8-0698-49d0-a65c-b5f45d724290") -> 716336b8-0698-49d0-a65c-b5f45d724175
A203: 961 | B203: Công ty TNHH INFOPLUS | C203: Tầng 6, tòa nhà Lucky, số 81 Trần Thái Tông, P.Dịch Vọng, Q.Cầu Giấy, Tp. Hà Nội, Việt Nam | F203: 1 | G203: 2021-09-27 11:26:32 | H203: 1588 | J203: 0108154862 | L203: =IFERROR(VLOOKUP(H203,users!$A$2:$D$205,2,FALSE),"716336b8-0698-49d0-a65c-b5f45d724290") -> 716336b8-0698-49d0-a65c-b5f45d724264
A204: 962 | B204: Công ty TNHH Công nghệ MegaCore | F204: 1 | G204: 2021-09-27 02:20:15 | H204: 1521 | L204: =IFERROR(VLOOKUP(H204,users!$A$2:$D$205,2,FALSE),"716336b8-0698-49d0-a65c-b5f45d724290") -> 716336b8-0698-49d0-a65c-b5f45d724191
A205: 963 | B205: Branch of GE Vietnam Ltd in Haiphong | C205: Land Plots H1-H6 & F13A, F13B, F14, F15 Nomura-Haiphong Industrial Zone, An Duong District,Hai Phong | F205: 1 | G205: 2021-09-28 10:53:23 | H205: 1536 | J205: 0101442678-002 | L205: =IFERROR(VLOOKUP(H205,users!$A$2:$D$205,2,FALSE),"716336b8-0698-49d0-a65c-b5f45d724290") -> 716336b8-0698-49d0-a65c-b5f45d724120
A206: 965 | B206: Ngân hàng TMCP Xăng dầu Petrolimex (PGBank) | F206: 1 | G206: 2021-10-01 05:03:18 | H206: 1515 | L206: =IFERROR(VLOOKUP(H206,users!$A$2:$D$205,2,FALSE),"716336b8-0698-49d0-a65c-b5f45d724290") -> 716336b8-0698-49d0-a65c-b5f45d724113
A207: 968 | B207: Ngân hàng TMCP Việt Á (Việt Á Bank) | C207: Tầng 4 và 5, Tòa nhà Samsora, 105 Chu Văn An, Phường Yết Kiêu, Quận Hà Đông, Hà Nội | F207: 1 | G207: 2021-10-06 08:53:19 | H207: 1515 | L207: =IFERROR(VLOOKUP(H207,users!$A$2:$D$205,2,FALSE),"716336b8-0698-49d0-a65c-b5f45d724290") -> 716336b8-0698-49d0-a65c-b5f45d724113
A208: 970 | B208: CÔNG TY TNHH HANWHA AERO ENGINES | C208: Lô CN1-02B-4-8, Khu công nghiệp công nghệ cao I, Khu công nghệ cao Hòa Lạc, Xã Hạ Bằng, Huyện Thạch Thất, Thành Phố Hà Nội. | D208: 02471099862 | E208: Doanh Nghiệp thuộc hạng mục đầu tư epe miễn thuế | F208: 1 | G208: 2021-10-11 03:58:54 | H208: 1533 | J208: 0107952393 | L208: =IFERROR(VLOOKUP(H208,users!$A$2:$D$205,2,FALSE),"716336b8-0698-49d0-a65c-b5f45d724290") -> 716336b8-0698-49d0-a65c-b5f45d724202
A209: 975 | B209: PEGATRON Corporation Group | C209: No.151, Warehouse w6,7,8,9,10,11,12 East-West Boulevard, VSIP Hai Phong Township Industrial & Service Park, Thuy Trieu Ward, Thuy Nguyen Distric, Vientnam | F209: 1 | G209: 2021-10-15 04:05:44 | H209: 1509 | L209: =IFERROR(VLOOKUP(H209,users!$A$2:$D$205,2,FALSE),"716336b8-0698-49d0-a65c-b5f45d724290") -> 716336b8-0698-49d0-a65c-b5f45d724230
A210: 1005 | B210: CÔNG TY CỔ PHẦN CHẾ TẠO BƠM HẢI DƯƠNG | C210: Số 2 Đường Ngô Quyền, P. Cẩm Thượng, TP Hải Dương, Tỉnh Hải Dương | D210: (+84-220) 3853 496 | E210: MST: 0800287016. | F210: 1 | G210: 2021-11-23 04:42:46 | H210: 1509 | J210: 0403000144 | L210: =IFERROR(VLOOKUP(H210,users!$A$2:$D$205,2,FALSE),"716336b8-0698-49d0-a65c-b5f45d724290") -> 716336b8-0698-49d0-a65c-b5f45d724230
A211: 1045 | B211: CÔNG TY CP VIỄN THÔNG ĐÔNG DƯƠNG TELECOM | C211: B001b, The Manor, Mỹ Đình 1, Quận Nam Từ Liêm, Hà Nội, Việt Nam | D211: (84-24) 7779 8666 | F211: 1 | G211: 2021-12-09 03:57:45 | H211: 1519 | L211: =IFERROR(VLOOKUP(H211,users!$A$2:$D$205,2,FALSE),"716336b8-0698-49d0-a65c-b5f45d724290") -> 716336b8-0698-49d0-a65c-b5f45d724175
A212: 1065 | B212: BẢO HIỂM XÃ HỘI VIỆT NAM | C212: Số 7, phố Tràng Thi, phường Hàng Trống, quận Hoàn Kiếm, Hà Nội | D212: 024.39387248 | F212: 1 | G212: 2021-12-14 10:58:05 | H212: 1680 | L212: =IFERROR(VLOOKUP(H212,users!$A$2:$D$205,2,FALSE),"716336b8-0698-49d0-a65c-b5f45d724290") -> 716336b8-0698-49d0-a65c-b5f45d724173
...

Sheet users
A1: ID | B1: ID Map | C1: Họ Và Tên
A2: 1577 | B2: 716336b8-0698-49d0-a65c-b5f45d724099 | C2: Nguyễn Minh Đức
A3: 1593 | B3: 716336b8-0698-49d0-a65c-b5f45d724100 | C3: Lê Thị Thảo
A4: 1658 | B4: 716336b8-0698-49d0-a65c-b5f45d724101 | C4: Quách Ngọc Phú
A5: 1660 | B5: 716336b8-0698-49d0-a65c-b5f45d724102 | C5: Nguyễn Thị Oanh
A6: 1663 | B6: 716336b8-0698-49d0-a65c-b5f45d724103 | C6: Nguyễn Phương Dung
A7: 1665 | B7: 716336b8-0698-49d0-a65c-b5f45d724104 | C7: Nguyễn Văn Quý
A8: 1666 | B8: 716336b8-0698-49d0-a65c-b5f45d724105 | C8: Vũ Đức Chính
A9: 1668 | B9: 716336b8-0698-49d0-a65c-b5f45d724106 | C9: Nguyễn Ngọc Quang
A10: 1671 | B10: 716336b8-0698-49d0-a65c-b5f45d724107 | C10: Phạm Gia Anh Thư
A11: 1673 | B11: 716336b8-0698-49d0-a65c-b5f45d724108 | C11: Nguyễn Kiêm Thắng
A12: 1675 | B12: 716336b8-0698-49d0-a65c-b5f45d724109 | C12: Trần Hữu Tuệ
A13: 1678 | B13: 716336b8-0698-49d0-a65c-b5f45d724110 | C13: Nguyễn Thế Giáp
... A205: 2011 | B205: 716336b8-0698-49d0-a65c-b5f45d724302 | C205: Vũ Linh Chi
